isqx/__init__.py
isqx/_citations.py
isqx/_core.py
isqx/_fmt.py
isqx/_iso80000.py
isqx/aerospace.py
isqx/chemistry.py
isqx/py.typed
isqx/usc.py
isqx/details/__init__.py
isqx/details/aerospace.py
isqx/details/chemistry.py
isqx/details/iso80000.py
isqx/mkdocs/__init__.py
isqx/mkdocs/extension.py
isqx/mkdocs/plugin.py
isqx/mkdocs/assets/css/detail-highlight.css
isqx/mkdocs/assets/js/cmap.mjs
isqx/mkdocs/assets/js/detail-highlight.mjs
isqx/mkdocs/assets/js/katex.mjs
isqx/mkdocs/templates/material/isqx/attribute.html.jinja
isqx/mkdocs/templates/material/isqx/function.html.jinja
isqx/mkdocs/templates/material/isqx/isqx.jinja
isqx-0.1.2.dist-info/METADATA
isqx-0.1.2.dist-info/WHEEL
isqx-0.1.2.dist-info/entry_points.txt
isqx-0.1.2.dist-info/licenses/LICENSE
isqx-0.1.2.dist-info/RECORD
