Metadata-Version: 2.4
Name: isqx
Version: 0.1.2
Summary: Units and quantity kinds defined by ISO/IEC 80000 and other subfields.
Project-URL: Repository, https://github.com/abc8747/isqx
Project-URL: Documentation, https://abc8747.github.io/isqx
Project-URL: Releases, https://github.com/abc8747/isqx/releases
Author-email: Abraham Cheung <abraham@ylcheung.com>
License-File: LICENSE
Classifier: Development Status :: 3 - Alpha
Classifier: Intended Audience :: Science/Research
Classifier: License :: OSI Approved :: MIT License
Classifier: Operating System :: OS Independent
Classifier: Programming Language :: Python
Classifier: Programming Language :: Python :: 3 :: Only
Classifier: Programming Language :: Python :: 3.9
Classifier: Programming Language :: Python :: 3.10
Classifier: Programming Language :: Python :: 3.11
Classifier: Programming Language :: Python :: 3.12
Classifier: Programming Language :: Python :: 3.13
Classifier: Programming Language :: Python :: 3.14
Classifier: Typing :: Typed
Requires-Python: >=3.9
Requires-Dist: typing-extensions>=4.0.0; python_version < '3.10'
